[
  {
    "op": "addeach",
    "file": "game:config/dialogue/sedna.json",
    "path": "/components/2/text/-",
    "value": [
      {
        "value": "dialogue-sedna-ask-tuningcylinder",
        "jumpTo": "tuningcylinder-response",
        "condition": { "variable": "player.triedsellsedna", "isValue": "true" }
      }
    ]
  },
  {
    "op": "addeach",
    "file": "game:config/dialogue/sedna.json",
    "path": "/components/-",
    "value": [
      {
        "code": "tuningcylinder-response",
        "owner": "sedna",
        "type": "talk",
        "text": [
          {
            "value": "dialogue-sedna-tuningcylinder-response"
          }
        ],
        "jumpTo": "tuningcylinder-selection"
      },
      {
        "code": "tuningcylinder-selection",
        "owner": "player",
        "type": "talk",
        "text": [
          {
            "value": "dialogue-sedna-no-unattuned-cylinder",
            "jumpTo": "tuningcylinder-no-unattuned",
            "condition": {
              "variable": "player.inventory",
              "isNotValue": "{type: 'item', code: 'moretuningcylinders:empty-tuningcylinder'}"
            }
          },
          {
            "value": "dialogue-sedna-tuningcylinder-nadiya-01",
            "jumpTo": "give-nadiya-01-trigger",
            "condition": {
              "variable": "player.inventory",
              "isValue": "{type: 'item', code: 'moretuningcylinders:empty-tuningcylinder'}"
            }
          },
          {
            "value": "dialogue-sedna-tuningcylinder-nadiya-04",
            "jumpTo": "give-nadiya-04-trigger",
            "condition": {
              "variable": "player.inventory",
              "isValue": "{type: 'item', code: 'moretuningcylinders:empty-tuningcylinder'}"
            }
          },
          {
            "value": "dialogue-sedna-tuningcylinder-nadiya-05",
            "jumpTo": "give-nadiya-05-trigger",
            "condition": {
              "variable": "player.inventory",
              "isValue": "{type: 'item', code: 'moretuningcylinders:empty-tuningcylinder'}"
            }
          },
          {
            "value": "dialogue-sedna-tuningcylinder-nadiya-06",
            "jumpTo": "give-nadiya-06-trigger",
            "condition": {
              "variable": "player.inventory",
              "isValue": "{type: 'item', code: 'moretuningcylinders:empty-tuningcylinder'}"
            }
          },
          {
            "value": "dialogue-sedna-tuningcylinder-nadiya-07",
            "jumpTo": "give-nadiya-07-trigger",
            "condition": {
              "variable": "player.inventory",
              "isValue": "{type: 'item', code: 'moretuningcylinders:empty-tuningcylinder'}"
            }
          },
          {
            "value": "dialogue-sedna-tuningcylinder-nadiya-02",
            "jumpTo": "give-nadiya-02-trigger",
            "condition": {
              "variable": "player.inventory",
              "isValue": "{type: 'item', code: 'moretuningcylinders:empty-tuningcylinder'}"
            }
          },
          {
            "value": "dialogue-sedna-tuningcylinder-nadiya-03",
            "jumpTo": "give-nadiya-03-trigger",
            "condition": {
              "variable": "player.inventory",
              "isValue": "{type: 'item', code: 'moretuningcylinders:empty-tuningcylinder'}"
            }
          },
          {
            "value": "dialogue-sedna-dont-want-tuningcylinder",
            "jumpTo": "test-dont-want-tuningcylinder",
            "condition": {
              "variable": "player.inventory",
              "isValue": "{type: 'item', code: 'moretuningcylinders:empty-tuningcylinder'}"
            }
          }
        ]
      },
      {
        "code": "tuningcylinder-no-unattuned",
        "owner": "sedna",
        "type": "talk",
        "text": [
          {
            "value": "dialogue-sedna-no-unattuned"
          }
        ],
        "jumpTo": "main"
      },
      {
        "code": "give-nadiya-01-trigger",
        "type": "trigger",
        "trigger": "takefrominventory",
        "triggerdata": {
          "type": "item",
          "code": "moretuningcylinders:empty-tuningcylinder"
        },
        "jumpTo": "tuningcylinder-give-nadiya-01"
      },
      {
        "code": "tuningcylinder-give-nadiya-01",
        "owner": "sedna",
        "type": "talk",
        "trigger": "giveitemstack",
        "triggerdata": {
          "type": "item",
          "code": "tuningcylinder-nadiya-01",
          "stacksize": 1
        },
        "setVariables": { "player.boughtCylinderFromSedna": "true" },
        "text": [
          {
            "value": "dialogue-sedna-tuningcylinder-give-nadiya-01"
          }
        ],
        "jumpTo": "main"
      },
      {
        "code": "give-nadiya-02-trigger",
        "type": "trigger",
        "trigger": "takefrominventory",
        "triggerdata": {
          "type": "item",
          "code": "moretuningcylinders:empty-tuningcylinder"
        },
        "jumpTo": "tuningcylinder-give-nadiya-02"
      },
      {
        "code": "tuningcylinder-give-nadiya-02",
        "owner": "sedna",
        "type": "talk",
        "trigger": "giveitemstack",
        "triggerdata": {
          "type": "item",
          "code": "tuningcylinder-nadiya-02",
          "stacksize": 1
        },
        "setVariables": { "player.boughtCylinderFromSedna": "true" },
        "text": [
          {
            "value": "dialogue-sedna-tuningcylinder-give-nadiya-02"
          }
        ],
        "jumpTo": "main"
      },
      {
        "code": "give-nadiya-03-trigger",
        "type": "trigger",
        "trigger": "takefrominventory",
        "triggerdata": {
          "type": "item",
          "code": "moretuningcylinders:empty-tuningcylinder"
        },
        "jumpTo": "tuningcylinder-give-nadiya-03"
      },
      {
        "code": "tuningcylinder-give-nadiya-03",
        "owner": "sedna",
        "type": "talk",
        "trigger": "giveitemstack",
        "triggerdata": {
          "type": "item",
          "code": "tuningcylinder-nadiya-03",
          "stacksize": 1
        },
        "setVariables": { "player.boughtCylinderFromSedna": "true" },
        "text": [
          {
            "value": "dialogue-sedna-tuningcylinder-give-nadiya-03"
          }
        ],
        "jumpTo": "main"
      },
      {
        "code": "give-nadiya-04-trigger",
        "type": "trigger",
        "trigger": "takefrominventory",
        "triggerdata": {
          "type": "item",
          "code": "moretuningcylinders:empty-tuningcylinder"
        },
        "jumpTo": "tuningcylinder-give-nadiya-04"
      },
      {
        "code": "tuningcylinder-give-nadiya-04",
        "owner": "sedna",
        "type": "talk",
        "trigger": "giveitemstack",
        "triggerdata": {
          "type": "item",
          "code": "tuningcylinder-nadiya-04",
          "stacksize": 1
        },
        "setVariables": { "player.boughtCylinderFromSedna": "true" },
        "text": [
          {
            "value": "dialogue-sedna-tuningcylinder-give-nadiya-04"
          }
        ],
        "jumpTo": "main"
      },
      {
        "code": "give-nadiya-05-trigger",
        "type": "trigger",
        "trigger": "takefrominventory",
        "triggerdata": {
          "type": "item",
          "code": "moretuningcylinders:empty-tuningcylinder"
        },
        "jumpTo": "tuningcylinder-give-nadiya-05"
      },
      {
        "code": "tuningcylinder-give-nadiya-05",
        "owner": "sedna",
        "type": "talk",
        "trigger": "giveitemstack",
        "triggerdata": {
          "type": "item",
          "code": "tuningcylinder-nadiya-05",
          "stacksize": 1
        },
        "setVariables": { "player.boughtCylinderFromSedna": "true" },
        "text": [
          {
            "value": "dialogue-sedna-tuningcylinder-give-nadiya-05"
          }
        ],
        "jumpTo": "main"
      },
      {
        "code": "give-nadiya-06-trigger",
        "type": "trigger",
        "trigger": "takefrominventory",
        "triggerdata": {
          "type": "item",
          "code": "moretuningcylinders:empty-tuningcylinder"
        },
        "jumpTo": "tuningcylinder-give-nadiya-06"
      },
      {
        "code": "tuningcylinder-give-nadiya-06",
        "owner": "sedna",
        "type": "talk",
        "trigger": "giveitemstack",
        "triggerdata": {
          "type": "item",
          "code": "tuningcylinder-nadiya-06",
          "stacksize": 1
        },
        "setVariables": { "player.boughtCylinderFromSedna": "true" },
        "text": [
          {
            "value": "dialogue-sedna-tuningcylinder-give-nadiya-06"
          }
        ],
        "jumpTo": "main"
      },
      {
        "code": "give-nadiya-07-trigger",
        "type": "trigger",
        "trigger": "takefrominventory",
        "triggerdata": {
          "type": "item",
          "code": "moretuningcylinders:empty-tuningcylinder"
        },
        "jumpTo": "tuningcylinder-give-nadiya-07"
      },
      {
        "code": "tuningcylinder-give-nadiya-07",
        "owner": "sedna",
        "type": "talk",
        "trigger": "giveitemstack",
        "triggerdata": {
          "type": "item",
          "code": "tuningcylinder-nadiya-07",
          "stacksize": 1
        },
        "setVariables": { "player.boughtCylinderFromSedna": "true" },
        "text": [
          {
            "value": "dialogue-sedna-tuningcylinder-give-nadiya-07"
          }
        ],
        "jumpTo": "main"
      },
      {
        "code": "test-dont-want-tuningcylinder",
        "owner": "sdna",
        "type": "condition",
        "variable": "player.boughtCylinderFromSedna",
        "isValue": "true",
        "thenJumpTo": "dont-want-tuningcylinder-nice",
        "elseJumpTo": "dont-want-tuningcylinder-rude"
      },
      {
        "code": "dont-want-tuningcylinder-nice",
        "owner": "sedna",
        "type": "talk",
        "text": [
          {
            "value": "dialogue-sedna-dont-want-tuningcylinder-nice-response"
          }
        ],
        "jumpTo": "main"
      },
      {
        "code": "dont-want-tuningcylinder-rude",
        "owner": "sedna",
        "type": "talk",
        "text": [
          {
            "value": "dialogue-sedna-dont-want-tuningcylinder-rude-response"
          }
        ],
        "jumpTo": "main"
      }
    ]
  }
]
